jxbase/__init__.py
jxbase/common_config.py
jxbase/jxbase_lib.py
jxbase/readme.txt
jxbase-3.0.dist-info/METADATA
jxbase-3.0.dist-info/WHEEL
jxbase-3.0.dist-info/top_level.txt
jxbase-3.0.dist-info/RECORD
